04_Counter/counter_async.v
module up_down_counter (
    input clk,
    input rst,          // asynchronous reset
    input load,         // synchronous load
    input up_down,      // 1 = up, 0 = down
    input [7:0] data,   // load value
    output reg [7:0] count
);

always @(posedge clk or posedge rst) begin
    if (rst)
        count <= 8'b00000000;     // async reset
    else if (load)
        count <= data;            // sync load
    else if (up_down)
        count <= count + 1;       // up count
    else
        count <= count - 1;       // down count
end

endmodule

04_Counter/tb_counter.v
`timescale 1ns/1ps

module tb_counter;

reg clk;
reg rst;
reg load;
reg up_down;
reg [7:0] data;
wire [7:0] count;

up_down_counter uut (
    .clk(clk),
    .rst(rst),
    .load(load),
    .up_down(up_down),
    .data(data),
    .count(count)
);

// clock generation
always #5 clk = ~clk;

initial begin
    $dumpfile("dump_counter.vcd");
    $dumpvars(0, tb_counter);

    clk = 0;
    rst = 1;
    load = 0;
    up_down = 1;
    data = 8'd10;

    #10 rst = 0;       // reset release

    #10 load = 1;      // load 10
    #10 load = 0;

    #50 up_down = 0;   // start down counting

    #50 rst = 1;       // async reset
    #10 rst = 0;

    #50 $finish;
end

endmodule

04_Counter/dump_counter.vcd
$date
	Tue Apr 21 16:30:13 2026
$end
$version
	Icarus Verilog
$end
$timescale
	1ps
$end
$scope module tb_counter $end
$var wire 8 ! count [7:0] $end
$var reg 1 " clk $end
$var reg 8 # data [7:0] $end
$var reg 1 $ load $end
$var reg 1 % rst $end
$var reg 1 & up_down $end
$scope module uut $end
$var wire 1 " clk $end
$var wire 8 ' data [7:0] $end
$var wire 1 $ load $end
$var wire 1 % rst $end
$var wire 1 & up_down $end
$var reg 8 ( count [7:0] $end
$upscope $end
$upscope $end
$enddefinitions $end
$comment Show the parameter values. $end
$dumpall
$end
#0
$dumpvars
b0 (
b1010 '
1&
1%
0$
b1010 #
0"
b0 !
$end
#5000
1"
#10000
0"
0%
#15000
b1 !
b1 (
1"
#20000
0"
1$
#25000
b1010 !
b1010 (
1"
#30000
0"
0$
#35000
b1011 !
b1011 (
1"
#40000
0"
#45000
b1100 !
b1100 (
1"
#50000
0"
#55000
b1101 !
b1101 (
1"
#60000
0"
#65000
b1110 !
b1110 (
1"
#70000
0"
#75000
b1111 !
b1111 (
1"
#80000
0"
0&
#85000
b1110 !
b1110 (
1"
#90000
0"
#95000
b1101 !
b1101 (
1"
#100000
0"
#105000
b1100 !
b1100 (
1"
#110000
0"
#115000
b1011 !
b1011 (
1"
#120000
0"
#125000
b1010 !
b1010 (
1"
#130000
b0 !
b0 (
0"
1%
#135000
1"
#140000
0"
0%
#145000
b11111111 !
b11111111 (
1"
#150000
0"
#155000
b11111110 !
b11111110 (
1"
#160000
0"
#165000
b11111101 !
b11111101 (
1"
#170000
0"
#175000
b11111100 !
b11111100 (
1"
#180000
0"
#185000
b11111011 !
b11111011 (
1"
