02_Encoder_Decoder/decoder3to8.v
module decoder3to8(
    input [2:0] A,
    output reg [7:0] Y
);

always @(*) begin
    case(A)
        3'b000: Y = 8'b00000001;
        3'b001: Y = 8'b00000010;
        3'b010: Y = 8'b00000100;
        3'b011: Y = 8'b00001000;
        3'b100: Y = 8'b00010000;
        3'b101: Y = 8'b00100000;
        3'b110: Y = 8'b01000000;
        3'b111: Y = 8'b10000000;
    endcase
end

endmodule

02_Encoder_Decoder/tb_decoder.v
`timescale 1ns/1ps

module tb_decoder;

reg [2:0] A;
wire [7:0] Y;

decoder3to8 uut(A, Y);

initial begin
$dumpfile("dump_decoder.vcd");
$dumpvars(0, tb_decoder);

A=0; #10;
A=1; #10;
A=2; #10;
A=3; #10;
A=4; #10;
A=5; #10;
A=6; #10;
A=7; #10;

$finish;
end

endmodule

02_Encoder_Decoder/dump_decoder.vcd
$date
	Tue Apr 21 14:58:29 2026
$end
$version
	Icarus Verilog
$end
$timescale
	1ps
$end
$scope module tb_decoder $end
$var wire 8 ! Y [7:0] $end
$var reg 3 " A [2:0] $end
$scope module uut $end
$var wire 3 # A [2:0] $end
$var reg 8 $ Y [7:0] $end
$upscope $end
$upscope $end
$enddefinitions $end
$comment Show the parameter values. $end
$dumpall
$end
#0
$dumpvars
b1 $
b0 #
b0 "
b1 !
$end
#10000
b10 !
b10 $
b1 "
b1 #
#20000
b100 !
b100 $
b10 "
b10 #
#30000
b1000 !
b1000 $
b11 "
b11 #
#40000
b10000 !
b10000 $
b100 "
b100 #
#50000
b100000 !
b100000 $
b101 "
b101 #
#60000
b1000000 !
b1000000 $
b110 "
b110 #
#70000
b10000000 !
b10000000 $
b111 "
b111 #
