02_Encoder_Decoder/encoder8to3.v
module encoder8to3(
    input [7:0] Y,
    output reg [2:0] A
);

always @(*) begin
    case(Y)
        8'b00000001: A = 3'b000;
        8'b00000010: A = 3'b001;
        8'b00000100: A = 3'b010;
        8'b00001000: A = 3'b011;
        8'b00010000: A = 3'b100;
        8'b00100000: A = 3'b101;
        8'b01000000: A = 3'b110;
        8'b10000000: A = 3'b111;
        default: A = 3'b000;
    endcase
end

endmodule

02_Encoder_Decoder/tb_encoder.v
`timescale 1ns/1ps

module tb_encoder;

reg [7:0] Y;
wire [2:0] A;

encoder8to3 uut(Y, A);

initial begin
$dumpfile("dump_encoder.vcd");
$dumpvars(0, tb_encoder);

Y=8'b00000001; #10;
Y=8'b00000010; #10;
Y=8'b00000100; #10;
Y=8'b00001000; #10;
Y=8'b00010000; #10;
Y=8'b00100000; #10;
Y=8'b01000000; #10;
Y=8'b10000000; #10;

$finish;
end

endmodule

02_Encoder_Decoder/dump_encoder.vcd
$date
	Tue Apr 21 15:07:53 2026
$end
$version
	Icarus Verilog
$end
$timescale
	1ps
$end
$scope module tb_encoder $end
$var wire 3 ! A [2:0] $end
$var reg 8 " Y [7:0] $end
$scope module uut $end
$var wire 8 # Y [7:0] $end
$var reg 3 $ A [2:0] $end
$upscope $end
$upscope $end
$enddefinitions $end
$comment Show the parameter values. $end
$dumpall
$end
#0
$dumpvars
b0 $
b1 #
b1 "
b0 !
$end
#10000
b1 !
b1 $
b10 "
b10 #
#20000
b10 !
b10 $
b100 "
b100 #
#30000
b11 !
b11 $
b1000 "
b1000 #
#40000
b100 !
b100 $
b10000 "
b10000 #
#50000
b101 !
b101 $
b100000 "
b100000 #
#60000
b110 !
b110 $
b1000000 "
b1000000 #
#70000
b111 !
b111 $
b10000000 "
b10000000 #
